bottleapi
