Metadata-Version: 1.0
Name: bottle-api
Version: 0.0.3
Summary: useful decorator for building WebAPI on Bottle web framework development
Home-page: https://github.com/tomotaka/bottle-api
Author: Tomotaka Ito
Author-email: tomotaka.ito@gmail.com
License: The MIT License (MIT)
